generalpackager/__init__.py
generalpackager/packager.py
generalpackager/packager_api.py
generalpackager/packager_environment.py
generalpackager/packager_files.py
generalpackager/packager_github.py
generalpackager/packager_metadata.py
generalpackager/packager_pypi.py
generalpackager/packager_relations.py
generalpackager/packager_workflow.py
generalpackager/api/localmodule.py
generalpackager/api/venv.py
generalpackager/api/venv_cruds.py
generalpackager/api/localrepo/base/localrepo.py
generalpackager/api/localrepo/base/localrepo_git.py
generalpackager/api/localrepo/base/localrepo_paths.py
generalpackager/api/localrepo/base/localrepo_target.py
generalpackager/api/localrepo/base/metadata.py
generalpackager/api/localrepo/node/localrepo_node.py
generalpackager/api/localrepo/node/metadata_node.py
generalpackager/api/localrepo/python/localrepo_python.py
generalpackager/api/localrepo/python/metadata_python.py
generalpackager/api/localrepo/top/target_helper.py
generalpackager/api/package_hosts/github.py
generalpackager/api/package_hosts/npm.py
generalpackager/api/package_hosts/pypi.py
generalpackager/api/shared/decos.py
generalpackager/api/shared/name.py
generalpackager/api/shared/owner.py
generalpackager/api/shared/path.py
generalpackager/api/shared/protocols.py
generalpackager/api/shared/target.py
generalpackager/api/shared/files/file.py
generalpackager/api/shared/files/file_fetcher.py
generalpackager/api/shared/files/helpers.py
generalpackager/api/shared/files/shared_files.py
generalpackager/api/shared/files/definitions/commit_editmsg.py
generalpackager/api/shared/files/definitions/examples.py
generalpackager/api/shared/files/definitions/exeproduct.py
generalpackager/api/shared/files/definitions/exetarget.py
generalpackager/api/shared/files/definitions/generate.py
generalpackager/api/shared/files/definitions/git_exclude.py
generalpackager/api/shared/files/definitions/gitignore.py
generalpackager/api/shared/files/definitions/index_js.py
generalpackager-0.5.10.dist-info/LICENSE
generalpackager-0.5.10.dist-info/METADATA
generalpackager-0.5.10.dist-info/WHEEL
generalpackager-0.5.10.dist-info/top_level.txt
generalpackager-0.5.10.dist-info/RECORD
