Metadata-Version: 2.1
Name: generalpackager
Version: 0.5.10
Summary: Tools to interface GitHub, PyPI, NPM and local modules / repos. Used for generating files to keep projects dry and synced. Tailored for ManderaGeneral for now.
Home-page: https://github.com/ManderaGeneral/generalpackager
Author: Rickard "Mandera" Abraham
Author-email: rickard.abraham@gmail.com
License: apache2
Classifier: Topic :: Software Development :: Build Tools
Classifier: Programming Language :: Python :: 3.8
Classifier: Programming Language :: Python :: 3.9
Classifier: Programming Language :: Python :: 3.10
Classifier: Programming Language :: Python :: 3.11
Classifier: Programming Language :: Python :: 3.12
Classifier: License :: OSI Approved :: Apache Software License
Classifier: Operating System :: Microsoft :: Windows
Classifier: Operating System :: POSIX :: Linux
License-File: LICENSE
Requires-Dist: generallibrary[table]
Requires-Dist: generalfile
Requires-Dist: requests
Requires-Dist: pyinstaller
Requires-Dist: coverage
Requires-Dist: setuptools
Requires-Dist: wheel
Requires-Dist: twine
